README.md
setup.py
guesser_game/GuesserGame.py
guesser_game/__init__.py
guesser_game/numberGuesserGame.py
guesser_game.egg-info/PKG-INFO
guesser_game.egg-info/SOURCES.txt
guesser_game.egg-info/dependency_links.txt
guesser_game.egg-info/top_level.txt