Metadata-Version: 2.1
Name: guesser-game
Version: 0.1.0
Summary: An easy funny game, which the computer will guess the number you have in mind
Home-page: https://github.com/mwpnava/Python-Code/tree/master/My_own_Python_package
Author: Wendy Navarrete
Author-email: navarrete.wen@gmail.com
License: UNKNOWN
Platform: UNKNOWN
Classifier: Programming Language :: Python :: 3.6
Classifier: License :: OSI Approved :: MIT License
Classifier: Operating System :: OS Independent
Classifier: Intended Audience :: Other Audience
Classifier: Topic :: Games/Entertainment
Requires-Python: >=3.6
